python-tree-walk/__init__.py
python-tree-walk/treewalk.py
tests/__init__.py
tests/randomtree.py
tests/tests.py
treewalk/__init__.py
treewalk/treewalk.py
treewalk-0.1.1.dist-info/LICENSE
treewalk-0.1.1.dist-info/METADATA
treewalk-0.1.1.dist-info/WHEEL
treewalk-0.1.1.dist-info/top_level.txt
treewalk-0.1.1.dist-info/RECORD
