Metadata-Version: 2.1
Name: treewalk
Version: 0.1.1
Summary: deep compare tree like structures
Home-page: https://github.com/uribrecher/python-tree-walk
Author: Uri Brecher
Author-email: uri.brecher@gmail.com
License: UNKNOWN
Platform: UNKNOWN
Classifier: Programming Language :: Python :: 3
Classifier: Programming Language :: Python :: 3.7
